{
  "id": "68e872a1-e5cf-44f2-9f18-1339f09646d2",
  "name": "12 Pt1 Wound Packing and Pressure Bandage PNG",
  "type": "document",
  "unit": "pixel",
  "width": 5100,
  "height": 6600,
  "stack": [
    {
      "name": "Background",
      "type": "image",
      "rect": {
        "x": 0,
        "y": 0,
        "w": 5100,
        "h": 6600,
        "r": 0
      },
      "opacity": 1,
      "locked": true,
      "visible": true,
      "link": "",
      "content": "cef7aa8d4c43.png"
    },
    {
      "name": "Shape 84",
      "type": "shape",
      "rect": {
        "x": 1400,
        "y": 4660,
        "w": 172,
        "h": 172,
        "r": 0
      },
      "opacity": 1,
      "locked": false,
      "visible": true,
      "link": "",
      "format": {
        "variant": "rectangle",
        "radii": 20,
        "fill": {
          "type": "color",
          "value": "#bd1c1e"
        }
      }
    },
    {
      "name": "Shape 83 Copy",
      "type": "shape",
      "rect": {
        "x": 3384,
        "y": 4681,
        "w": 159,
        "h": 137,
        "r": 0
      },
      "opacity": 1,
      "locked": false,
      "visible": true,
      "link": "",
      "format": {
        "variant": "rectangle",
        "radii": 20,
        "fill": {
          "type": "color",
          "value": "#bd1c1e"
        }
      }
    },
    {
      "name": "Shape 67",
      "type": "shape",
      "rect": {
        "x": 2548,
        "y": 1314,
        "w": 299,
        "h": 278,
        "r": 0
      },
      "opacity": 1,
      "locked": false,
      "visible": true,
      "link": "",
      "format": {
        "variant": "rectangle",
        "radii": 20,
        "fill": {
          "type": "color",
          "value": "#ffffff"
        }
      }
    },
    {
      "name": "АБО..",
      "type": "text",
      "rect": {
        "x": 3092,
        "y": 4732,
        "w": 228,
        "h": 110,
        "r": 0
      },
      "opacity": 1,
      "locked": false,
      "visible": true,
      "link": "",
      "content": "АБО",
      "format": {
        "size": 80,
        "align": "center",
        "bold": true,
        "italic": false,
        "underline": false,
        "uppercase": false,
        "linespace": 0,
        "letterspace": 0,
        "font": {
          "name": "Arial",
          "content": "arial.woff"
        },
        "fill": {
          "type": "color",
          "value": "#f00505"
        }
      },
      "style": {
        "outline": {
          "size": 0.3,
          "color": "#000000",
          "punch": false,
          "distance": 0,
          "direction": 305
        }
      }
    },
    {
      "name": "Продовження на наступній ..",
      "type": "text",
      "rect": {
        "x": 3597,
        "y": 6335,
        "w": 1520,
        "h": 105,
        "r": 0
      },
      "opacity": 1,
      "locked": false,
      "visible": true,
      "link": "",
      "content": "Продовження на наступній сторінці…",
      "format": {
        "size": 76,
        "align": "left",
        "bold": true,
        "italic": false,
        "underline": false,
        "uppercase": false,
        "linespace": 0,
        "letterspace": 0,
        "font": {
          "name": "Arial",
          "content": "arial.woff"
        },
        "fill": {
          "type": "color",
          "value": "#000000"
        }
      }
    },
    {
      "name": "______________________ Як..",
      "type": "text",
      "rect": {
        "x": 260,
        "y": 6155,
        "w": 3396,
        "h": 271,
        "r": 0
      },
      "opacity": 1,
      "locked": false,
      "visible": true,
      "link": "",
      "content": "______________________ Якщо бандаж має пластиковий елемент для тиску, проведіть еластичний бинт крізь отвір елемента та розверніть еластичний бинт у зворотному напрямку над пластиковим елементом для тиску, таким чином притиснувши його до подушечки. ",
      "format": {
        "size": 76,
        "align": "left",
        "bold": true,
        "italic": false,
        "underline": false,
        "uppercase": false,
        "linespace": -0.1,
        "letterspace": 0,
        "font": {
          "name": "Arial",
          "content": "arial.woff"
        },
        "fill": {
          "type": "color",
          "value": "#000000"
        }
      }
    },
    {
      "name": "ПРИМІТКА ДО КРОКУ 11 : ..",
      "type": "text",
      "rect": {
        "x": 260,
        "y": 6146,
        "w": 3396,
        "h": 105,
        "r": 0
      },
      "opacity": 1,
      "locked": false,
      "visible": true,
      "link": "",
      "content": "ПРИМІТКА ДО КРОКУ 11 : ",
      "format": {
        "size": 76,
        "align": "left",
        "bold": true,
        "italic": false,
        "underline": false,
        "uppercase": false,
        "linespace": -0.1,
        "letterspace": 0,
        "font": {
          "name": "Arial",
          "content": "arial.woff"
        },
        "fill": {
          "type": "color",
          "value": "#f00505"
        }
      },
      "style": {
        "outline": {
          "size": 0.3,
          "color": "#000000",
          "punch": false,
          "distance": 0,
          "direction": 305
        }
      }
    },
    {
      "name": "Щільно ОБЕРНІТЬ еластични..",
      "type": "text",
      "rect": {
        "x": 3548,
        "y": 5804,
        "w": 1260,
        "h": 401,
        "r": 0
      },
      "opacity": 1,
      "locked": false,
      "visible": true,
      "link": "",
      "content": "Щільно ОБЕРНІТЬ еластичний бинт бандажа навколо кінцівки, переконавшись, що краї подушечки повністю покриті ним (див. примітку нижче).",
      "format": {
        "size": 76,
        "align": "left",
        "bold": true,
        "italic": false,
        "underline": false,
        "uppercase": false,
        "linespace": -0.22,
        "letterspace": 0,
        "font": {
          "name": "Arial",
          "content": "arial.woff"
        },
        "fill": {
          "type": "color",
          "value": "#000000"
        }
      }
    },
    {
      "name": "РОЗМІСТІТЬ подушечку банд..",
      "type": "text",
      "rect": {
        "x": 2020,
        "y": 5808,
        "w": 1329,
        "h": 327,
        "r": 0
      },
      "opacity": 1,
      "locked": false,
      "visible": true,
      "link": "",
      "content": "РОЗМІСТІТЬ подушечку бандажа над раною або поверх накладеної пов’язки, продовжуючи застосовувати прямий тиск.",
      "format": {
        "size": 76,
        "align": "left",
        "bold": true,
        "italic": false,
        "underline": false,
        "uppercase": false,
        "linespace": -0.22,
        "letterspace": 0,
        "font": {
          "name": "Arial",
          "content": "arial.woff"
        },
        "fill": {
          "type": "color",
          "value": "#000000"
        }
      }
    },
    {
      "name": "ВИЙМІТЬ компресійний банд..",
      "type": "text",
      "rect": {
        "x": 489,
        "y": 5808,
        "w": 1204,
        "h": 179,
        "r": 0
      },
      "opacity": 1,
      "locked": false,
      "visible": true,
      "link": "",
      "content": "ВИЙМІТЬ компресійний бандаж з обгортки та упаковки.",
      "format": {
        "size": 76,
        "align": "left",
        "bold": true,
        "italic": false,
        "underline": false,
        "uppercase": false,
        "linespace": -0.22,
        "letterspace": 0,
        "font": {
          "name": "Arial",
          "content": "arial.woff"
        },
        "fill": {
          "type": "color",
          "value": "#000000"
        }
      }
    },
    {
      "name": "Якщо використано звичайни..",
      "type": "text",
      "rect": {
        "x": 3570,
        "y": 4620,
        "w": 1270,
        "h": 401,
        "r": 0
      },
      "opacity": 1,
      "locked": false,
      "visible": true,
      "link": "",
      "content": "Якщо використано звичайний бинт - додайте ще один і утримуйте тиск на рану (впродовж 3 хв), поки кровотеча не зупиниться.",
      "format": {
        "size": 76,
        "align": "left",
        "bold": true,
        "italic": false,
        "underline": false,
        "uppercase": false,
        "linespace": -0.22,
        "letterspace": 0,
        "font": {
          "name": "Arial",
          "content": "arial.woff"
        },
        "fill": {
          "type": "color",
          "value": "#000000"
        }
      }
    },
    {
      "name": "ЯКЩО КРОВОТЕЧА НЕ ЗУПИНИЛ..",
      "type": "text",
      "rect": {
        "x": 320,
        "y": 4672,
        "w": 1452,
        "h": 197,
        "r": 0
      },
      "opacity": 1,
      "locked": false,
      "visible": true,
      "link": "",
      "content": "ЯКЩО КРОВОТЕЧА НЕ ЗУПИНИЛАСЬ:",
      "format": {
        "size": 80,
        "align": "left",
        "bold": true,
        "italic": false,
        "underline": false,
        "uppercase": false,
        "linespace": -0.1,
        "letterspace": 0,
        "font": {
          "name": "Arial",
          "content": "arial.woff"
        },
        "fill": {
          "type": "color",
          "value": "#f00505"
        }
      },
      "style": {
        "outline": {
          "size": 0.3,
          "color": "#000000",
          "punch": false,
          "distance": 0,
          "direction": 305
        }
      }
    },
    {
      "name": "Shape 83",
      "type": "shape",
      "rect": {
        "x": 1840,
        "y": 4660,
        "w": 172,
        "h": 172,
        "r": 0
      },
      "opacity": 1,
      "locked": false,
      "visible": true,
      "link": "",
      "format": {
        "variant": "rectangle",
        "radii": 20,
        "fill": {
          "type": "color",
          "value": "#ffffff"
        }
      }
    },
    {
      "name": "Якщо використано гемостат..",
      "type": "text",
      "rect": {
        "x": 1605,
        "y": 4623,
        "w": 1478,
        "h": 327,
        "r": 0
      },
      "opacity": 1,
      "locked": false,
      "visible": true,
      "link": "",
      "content": "Якщо використано гемостатичний бинт – вийміть його та проведіть повторне тампонування новим гемостатичним бинтом, починаючи від КРОКУ 3.",
      "format": {
        "size": 76,
        "align": "left",
        "bold": true,
        "italic": false,
        "underline": false,
        "uppercase": false,
        "linespace": -0.22,
        "letterspace": 0,
        "font": {
          "name": "Arial",
          "content": "arial.woff"
        },
        "fill": {
          "type": "color",
          "value": "#000000"
        }
      }
    },
    {
      "name": "ПОВТОРНО ОЦІНІТЬ, чи кров..",
      "type": "text",
      "rect": {
        "x": 3556,
        "y": 3989,
        "w": 1282,
        "h": 327,
        "r": 0
      },
      "opacity": 1,
      "locked": false,
      "visible": true,
      "link": "",
      "content": "ПОВТОРНО ОЦІНІТЬ, чи кровотеча зупинилась. Якщо це так, одночасно утримуючи тиск, залишіть бинт у рані. ",
      "format": {
        "size": 76,
        "align": "left",
        "bold": true,
        "italic": false,
        "underline": false,
        "uppercase": false,
        "linespace": -0.22,
        "letterspace": 0,
        "font": {
          "name": "Arial",
          "content": "arial.woff"
        },
        "fill": {
          "type": "color",
          "value": "#000000"
        }
      }
    },
    {
      "name": "Після тампонування рани У..",
      "type": "text",
      "rect": {
        "x": 2020,
        "y": 3989,
        "w": 1332,
        "h": 327,
        "r": 0
      },
      "opacity": 1,
      "locked": false,
      "visible": true,
      "link": "",
      "content": "Після тампонування рани УТРИМУЙТЕ тиск впродовж мінімум 3 хв., допоки кровотеча не зупиниться.",
      "format": {
        "size": 76,
        "align": "left",
        "bold": true,
        "italic": false,
        "underline": false,
        "uppercase": false,
        "linespace": -0.22,
        "letterspace": 0,
        "font": {
          "name": "Arial",
          "content": "arial.woff"
        },
        "fill": {
          "type": "color",
          "value": "#000000"
        }
      }
    },
    {
      "name": "_____________________ Якщ..",
      "type": "text",
      "rect": {
        "x": 347,
        "y": 4337,
        "w": 2785,
        "h": 179,
        "r": 0
      },
      "opacity": 1,
      "locked": false,
      "visible": true,
      "link": "",
      "content": "_____________________ Якщо гемостатична пов’язка або бинт не виступає над шкірою на 3-5 см, накладіть додаткову гемостатичну пов’язку або бинт.",
      "format": {
        "size": 76,
        "align": "left",
        "bold": true,
        "italic": false,
        "underline": false,
        "uppercase": false,
        "linespace": -0.22,
        "letterspace": 0,
        "font": {
          "name": "Arial",
          "content": "arial.woff"
        },
        "fill": {
          "type": "color",
          "value": "#000000"
        }
      }
    },
    {
      "name": "ПРИМІТКА ДО КРОКУ 5:..",
      "type": "text",
      "rect": {
        "x": 347,
        "y": 4325,
        "w": 3053,
        "h": 105,
        "r": 0
      },
      "opacity": 1,
      "locked": false,
      "visible": true,
      "link": "",
      "content": "ПРИМІТКА ДО КРОКУ 5:",
      "format": {
        "size": 76,
        "align": "left",
        "bold": true,
        "italic": false,
        "underline": false,
        "uppercase": false,
        "linespace": -0.22,
        "letterspace": 0,
        "font": {
          "name": "Arial",
          "content": "arial.woff"
        },
        "fill": {
          "type": "color",
          "value": "#f00505"
        }
      },
      "style": {
        "outline": {
          "size": 0.3,
          "color": "#000000",
          "punch": false,
          "distance": 0,
          "direction": 305
        }
      }
    },
    {
      "name": "Переконайтесь, що гемоста..",
      "type": "text",
      "rect": {
        "x": 496,
        "y": 3989,
        "w": 1277,
        "h": 327,
        "r": 0
      },
      "opacity": 1,
      "locked": false,
      "visible": true,
      "link": "",
      "content": "Переконайтесь, що гемостатична пов’язка або бинт заповнює всю порожнину рани та виступає над шкірою на 3-5 см.",
      "format": {
        "size": 76,
        "align": "left",
        "bold": true,
        "italic": false,
        "underline": false,
        "uppercase": false,
        "linespace": -0.22,
        "letterspace": 0,
        "font": {
          "name": "Arial",
          "content": "arial.woff"
        },
        "fill": {
          "type": "color",
          "value": "#000000"
        }
      }
    },
    {
      "name": "_____________________ Для..",
      "type": "text",
      "rect": {
        "x": 710,
        "y": 2902,
        "w": 4252,
        "h": 105,
        "r": 0
      },
      "opacity": 1,
      "locked": false,
      "visible": true,
      "link": "",
      "content": "_____________________ Для зупинки кровотечі може знадобитися більше однієї гемостатичної пов’язки чи бинта. ",
      "format": {
        "size": 76,
        "align": "left",
        "bold": true,
        "italic": false,
        "underline": false,
        "uppercase": false,
        "linespace": -0.22,
        "letterspace": 0,
        "font": {
          "name": "Arial",
          "content": "arial.woff"
        },
        "fill": {
          "type": "color",
          "value": "#000000"
        }
      }
    },
    {
      "name": "_________________________..",
      "type": "text",
      "rect": {
        "x": 710,
        "y": 3007,
        "w": 4252,
        "h": 105,
        "r": 0
      },
      "opacity": 1,
      "locked": false,
      "visible": true,
      "link": "",
      "content": "______________________________ Якщо в рані є стороннє тіло, забинтуйте його на місці. Не виймайте предмет.",
      "format": {
        "size": 76,
        "align": "left",
        "bold": true,
        "italic": false,
        "underline": false,
        "uppercase": false,
        "linespace": -0.22,
        "letterspace": 0,
        "font": {
          "name": "Arial",
          "content": "arial.woff"
        },
        "fill": {
          "type": "color",
          "value": "#000000"
        }
      }
    },
    {
      "name": "_____________________ Щіл..",
      "type": "text",
      "rect": {
        "x": 710,
        "y": 2797,
        "w": 4252,
        "h": 105,
        "r": 0
      },
      "opacity": 1,
      "locked": false,
      "visible": true,
      "link": "",
      "content": "_____________________ Щільно заповніть і затампонуйте всю порожнину рани, зберігаючи прямий тиск на рану. ",
      "format": {
        "size": 76,
        "align": "left",
        "bold": true,
        "italic": false,
        "underline": false,
        "uppercase": false,
        "linespace": -0.22,
        "letterspace": 0,
        "font": {
          "name": "Arial",
          "content": "arial.woff"
        },
        "fill": {
          "type": "color",
          "value": "#000000"
        }
      }
    },
    {
      "name": "ПРИМІТКА ДО КРОКУ 4 :..",
      "type": "text",
      "rect": {
        "x": 710,
        "y": 2788,
        "w": 4252,
        "h": 105,
        "r": 0
      },
      "opacity": 1,
      "locked": false,
      "visible": true,
      "link": "",
      "content": "ПРИМІТКА ДО КРОКУ 4 :",
      "format": {
        "size": 76,
        "align": "left",
        "bold": true,
        "italic": false,
        "underline": false,
        "uppercase": false,
        "linespace": -0.22,
        "letterspace": 0,
        "font": {
          "name": "Arial",
          "content": "arial.woff"
        },
        "fill": {
          "type": "color",
          "value": "#f00505"
        }
      },
      "style": {
        "outline": {
          "size": 0.3,
          "color": "#000000",
          "punch": false,
          "distance": 0,
          "direction": 305
        }
      }
    },
    {
      "name": "ПРИМІТКА ДО КРОКУ 4 :..",
      "type": "text",
      "rect": {
        "x": 710,
        "y": 2893,
        "w": 4252,
        "h": 105,
        "r": 0
      },
      "opacity": 1,
      "locked": false,
      "visible": true,
      "link": "",
      "content": "ПРИМІТКА ДО КРОКУ 4 :",
      "format": {
        "size": 76,
        "align": "left",
        "bold": true,
        "italic": false,
        "underline": false,
        "uppercase": false,
        "linespace": -0.22,
        "letterspace": 0,
        "font": {
          "name": "Arial",
          "content": "arial.woff"
        },
        "fill": {
          "type": "color",
          "value": "#f00505"
        }
      },
      "style": {
        "outline": {
          "size": 0.3,
          "color": "#000000",
          "punch": false,
          "distance": 0,
          "direction": 305
        }
      }
    },
    {
      "name": "ЗАСТЕРЕЖЕННЯ ЩОДО КРОКУ 4..",
      "type": "text",
      "rect": {
        "x": 710,
        "y": 2998,
        "w": 4252,
        "h": 105,
        "r": 0
      },
      "opacity": 1,
      "locked": false,
      "visible": true,
      "link": "",
      "content": "ЗАСТЕРЕЖЕННЯ ЩОДО КРОКУ 4 :",
      "format": {
        "size": 76,
        "align": "left",
        "bold": true,
        "italic": false,
        "underline": false,
        "uppercase": false,
        "linespace": -0.22,
        "letterspace": 0,
        "font": {
          "name": "Arial",
          "content": "arial.woff"
        },
        "fill": {
          "type": "color",
          "value": "#f00505"
        }
      },
      "style": {
        "outline": {
          "size": 0.3,
          "color": "#000000",
          "punch": false,
          "distance": 0,
          "direction": 305
        }
      }
    },
    {
      "name": "Проведіть щільне ТАМПОНУВ..",
      "type": "text",
      "rect": {
        "x": 3560,
        "y": 2492,
        "w": 1436,
        "h": 253,
        "r": 0
      },
      "opacity": 1,
      "locked": false,
      "visible": true,
      "link": "",
      "content": "Проведіть щільне ТАМПОНУВАННЯ рани безпосередньо в місці активної кровотечі.",
      "format": {
        "size": 76,
        "align": "left",
        "bold": true,
        "italic": false,
        "underline": false,
        "uppercase": false,
        "linespace": -0.22,
        "letterspace": 0,
        "font": {
          "name": "Arial",
          "content": "arial.woff"
        },
        "fill": {
          "type": "color",
          "value": "#000000"
        }
      }
    },
    {
      "name": "ВИЙМІТЬ гемостатичну пов’..",
      "type": "text",
      "rect": {
        "x": 2016,
        "y": 2492,
        "w": 1252,
        "h": 179,
        "r": 0
      },
      "opacity": 1,
      "locked": false,
      "visible": true,
      "link": "",
      "content": "ВИЙМІТЬ гемостатичну пов’язку зі стерильного упакування.",
      "format": {
        "size": 76,
        "align": "left",
        "bold": true,
        "italic": false,
        "underline": false,
        "uppercase": false,
        "linespace": -0.22,
        "letterspace": 0,
        "font": {
          "name": "Arial",
          "content": "arial.woff"
        },
        "fill": {
          "type": "color",
          "value": "#000000"
        }
      }
    },
    {
      "name": "ВИЯВІТЬ джерело найбільш ..",
      "type": "text",
      "rect": {
        "x": 486,
        "y": 2492,
        "w": 1228,
        "h": 253,
        "r": 0
      },
      "opacity": 1,
      "locked": false,
      "visible": true,
      "link": "",
      "content": "ВИЯВІТЬ джерело найбільш активної кровотечі та застосуйте прямий тиск на рану.",
      "format": {
        "size": 76,
        "align": "left",
        "bold": true,
        "italic": false,
        "underline": false,
        "uppercase": false,
        "linespace": -0.22,
        "letterspace": 0,
        "font": {
          "name": "Arial",
          "content": "arial.woff"
        },
        "fill": {
          "type": "color",
          "value": "#000000"
        }
      }
    },
    {
      "name": "__________ За необхідност..",
      "type": "text",
      "rect": {
        "x": 2654,
        "y": 1433,
        "w": 2256,
        "h": 188,
        "r": 0
      },
      "opacity": 1,
      "locked": false,
      "visible": true,
      "link": "",
      "content": "__________ За необхідності зніміть одяг та спорядження з постраждалого.",
      "format": {
        "size": 76,
        "align": "left",
        "bold": true,
        "italic": false,
        "underline": false,
        "uppercase": false,
        "linespace": -0.1,
        "letterspace": 0,
        "font": {
          "name": "Arial",
          "content": "arial.woff"
        },
        "fill": {
          "type": "color",
          "value": "#000000"
        }
      }
    },
    {
      "name": "ПРИМІТКА : ..",
      "type": "text",
      "rect": {
        "x": 2654,
        "y": 1433,
        "w": 2256,
        "h": 105,
        "r": 0
      },
      "opacity": 1,
      "locked": false,
      "visible": true,
      "link": "",
      "content": "ПРИМІТКА : ",
      "format": {
        "size": 76,
        "align": "left",
        "bold": true,
        "italic": false,
        "underline": false,
        "uppercase": false,
        "linespace": -0.1,
        "letterspace": 0,
        "font": {
          "name": "Arial",
          "content": "arial.woff"
        },
        "fill": {
          "type": "color",
          "value": "#f00505"
        }
      },
      "style": {
        "outline": {
          "size": 0.3,
          "color": "#000000",
          "punch": false,
          "distance": 0,
          "direction": 305
        }
      }
    },
    {
      "name": "Screen Shot 2023-10-02 at 12.58.46 AM.png",
      "type": "image",
      "rect": {
        "x": 2480,
        "y": 1341,
        "w": 174,
        "h": 185,
        "r": 0
      },
      "opacity": 1,
      "locked": false,
      "visible": true,
      "link": "",
      "content": "bbe79fa04a2c.png"
    },
    {
      "name": "РОЗКРИЙТЕ місце поранення..",
      "type": "text",
      "rect": {
        "x": 2654,
        "y": 1328,
        "w": 2338,
        "h": 105,
        "r": 0
      },
      "opacity": 1,
      "locked": false,
      "visible": true,
      "link": "",
      "content": "РОЗКРИЙТЕ місце поранення та огляньте джерело кровотечі. ",
      "format": {
        "size": 76,
        "align": "left",
        "bold": true,
        "italic": false,
        "underline": false,
        "uppercase": false,
        "linespace": -0.22,
        "letterspace": 0,
        "font": {
          "name": "Arial",
          "content": "arial.woff"
        },
        "fill": {
          "type": "color",
          "value": "#000000"
        }
      }
    },
    {
      "name": "ПОДБАЙТЕ про засоби індив..",
      "type": "text",
      "rect": {
        "x": 600,
        "y": 1344,
        "w": 1880,
        "h": 105,
        "r": 0
      },
      "opacity": 1,
      "locked": false,
      "visible": true,
      "link": "",
      "content": "ПОДБАЙТЕ про засоби індивідуального захисту. ",
      "format": {
        "size": 76,
        "align": "left",
        "bold": true,
        "italic": false,
        "underline": false,
        "uppercase": false,
        "linespace": -0.22,
        "letterspace": 0,
        "font": {
          "name": "Arial",
          "content": "arial.woff"
        },
        "fill": {
          "type": "color",
          "value": "#000000"
        }
      }
    },
    {
      "name": "__________ Якщо доступний..",
      "type": "text",
      "rect": {
        "x": 600,
        "y": 1449,
        "w": 1820,
        "h": 188,
        "r": 0
      },
      "opacity": 1,
      "locked": false,
      "visible": true,
      "link": "",
      "content": "__________ Якщо доступний боєць-рятувальник, скеруйте його вам на допомогу.",
      "format": {
        "size": 76,
        "align": "left",
        "bold": true,
        "italic": false,
        "underline": false,
        "uppercase": false,
        "linespace": -0.1,
        "letterspace": 0,
        "font": {
          "name": "Arial",
          "content": "arial.woff"
        },
        "fill": {
          "type": "color",
          "value": "#000000"
        }
      }
    },
    {
      "name": "ПРИМІТКА :..",
      "type": "text",
      "rect": {
        "x": 600,
        "y": 1449,
        "w": 1820,
        "h": 105,
        "r": 0
      },
      "opacity": 1,
      "locked": false,
      "visible": true,
      "link": "",
      "content": "ПРИМІТКА :",
      "format": {
        "size": 76,
        "align": "left",
        "bold": true,
        "italic": false,
        "underline": false,
        "uppercase": false,
        "linespace": -0.1,
        "letterspace": 0,
        "font": {
          "name": "Arial",
          "content": "arial.woff"
        },
        "fill": {
          "type": "color",
          "value": "#f00505"
        }
      },
      "style": {
        "outline": {
          "size": 0.3,
          "color": "#000000",
          "punch": false,
          "distance": 0,
          "direction": 305
        }
      }
    },
    {
      "name": "ТАМПОНУВАННЯ РАНИ ТА НАКЛ..",
      "type": "text",
      "rect": {
        "x": 248,
        "y": 752,
        "w": 4248,
        "h": 507,
        "r": 0
      },
      "opacity": 1,
      "locked": false,
      "visible": true,
      "link": "",
      "content": "ТАМПОНУВАННЯ РАНИ ТА НАКЛАДАННЯ КОМПРЕСІЙНОГО БАНДАЖА",
      "format": {
        "size": 200,
        "align": "left",
        "bold": true,
        "italic": false,
        "underline": false,
        "uppercase": false,
        "linespace": 0,
        "letterspace": 0,
        "font": {
          "name": "Arial",
          "content": "arial.woff"
        },
        "fill": {
          "type": "color",
          "value": "#000000"
        }
      }
    },
    {
      "name": "хвилини..",
      "type": "text",
      "rect": {
        "x": 1932,
        "y": 3752,
        "w": 284,
        "h": 79,
        "r": 0
      },
      "opacity": 1,
      "locked": false,
      "visible": true,
      "link": "",
      "content": "хвилини",
      "format": {
        "size": 58,
        "align": "center",
        "bold": true,
        "italic": false,
        "underline": false,
        "uppercase": false,
        "linespace": 0,
        "letterspace": 0,
        "font": {
          "name": "Arial",
          "content": "arial.woff"
        },
        "fill": {
          "type": "color",
          "value": "#000000"
        }
      }
    },
    {
      "name": "08.1..",
      "type": "text",
      "rect": {
        "x": 1357,
        "y": 4705,
        "w": 267,
        "h": 106,
        "r": 0
      },
      "opacity": 1,
      "locked": false,
      "visible": true,
      "link": "",
      "content": "08.1",
      "format": {
        "size": 80,
        "align": "center",
        "bold": true,
        "italic": false,
        "underline": false,
        "uppercase": false,
        "linespace": 0,
        "letterspace": 0,
        "font": {
          "name": "Arial",
          "content": "arial.woff"
        },
        "fill": {
          "type": "color",
          "value": "#ffffff"
        }
      }
    },
    {
      "name": "08.2..",
      "type": "text",
      "rect": {
        "x": 3330,
        "y": 4705,
        "w": 267,
        "h": 106,
        "r": 0
      },
      "opacity": 1,
      "locked": false,
      "visible": true,
      "link": "",
      "content": "08.2",
      "format": {
        "size": 80,
        "align": "center",
        "bold": true,
        "italic": false,
        "underline": false,
        "uppercase": false,
        "linespace": 0,
        "letterspace": 0,
        "font": {
          "name": "Arial",
          "content": "arial.woff"
        },
        "fill": {
          "type": "color",
          "value": "#ffffff"
        }
      }
    },
    {
      "name": "Shape 55 Copy",
      "type": "shape",
      "rect": {
        "x": 851,
        "y": 1694,
        "w": 841,
        "h": 120,
        "r": 0
      },
      "opacity": 1,
      "locked": false,
      "visible": true,
      "link": "",
      "format": {
        "variant": "rounded",
        "radii": 20,
        "fill": {
          "type": "color",
          "value": "#ffffff"
        }
      },
      "style": {
        "outline": {
          "size": 16,
          "color": "#bd1c1e"
        }
      }
    },
    {
      "name": "Shape 55 Copy",
      "type": "shape",
      "rect": {
        "x": 1880,
        "y": 1683,
        "w": 841,
        "h": 120,
        "r": 0
      },
      "opacity": 1,
      "locked": false,
      "visible": true,
      "link": "",
      "format": {
        "variant": "rounded",
        "radii": 20,
        "fill": {
          "type": "color",
          "value": "#ffffff"
        }
      },
      "style": {
        "outline": {
          "size": 16,
          "color": "#bd1c1e"
        }
      }
    },
    {
      "name": "Shape 55 Copy",
      "type": "shape",
      "rect": {
        "x": 3428,
        "y": 1693,
        "w": 841,
        "h": 120,
        "r": 0
      },
      "opacity": 1,
      "locked": false,
      "visible": true,
      "link": "",
      "format": {
        "variant": "rounded",
        "radii": 20,
        "fill": {
          "type": "color",
          "value": "#ffffff"
        }
      },
      "style": {
        "outline": {
          "size": 16,
          "color": "#bd1c1e"
        }
      }
    },
    {
      "name": "Shape 55 Copy",
      "type": "shape",
      "rect": {
        "x": 3400,
        "y": 3179,
        "w": 841,
        "h": 120,
        "r": 0
      },
      "opacity": 1,
      "locked": false,
      "visible": true,
      "link": "",
      "format": {
        "variant": "rounded",
        "radii": 20,
        "fill": {
          "type": "color",
          "value": "#ffffff"
        }
      },
      "style": {
        "outline": {
          "size": 16,
          "color": "#bd1c1e"
        }
      }
    },
    {
      "name": "Shape 55 Copy",
      "type": "shape",
      "rect": {
        "x": 1864,
        "y": 5653,
        "w": 841,
        "h": 120,
        "r": 0
      },
      "opacity": 1,
      "locked": false,
      "visible": true,
      "link": "",
      "format": {
        "variant": "rounded",
        "radii": 20,
        "fill": {
          "type": "color",
          "value": "#ffffff"
        }
      },
      "style": {
        "outline": {
          "size": 16,
          "color": "#bd1c1e"
        }
      }
    },
    {
      "name": "УТРИМУЙТЕ ТИСК..",
      "type": "text",
      "rect": {
        "x": 851,
        "y": 1720,
        "w": 842,
        "h": 83,
        "r": 0
      },
      "opacity": 1,
      "locked": false,
      "visible": true,
      "link": "",
      "content": "УТРИМУЙТЕ ТИСК",
      "format": {
        "size": 60,
        "align": "center",
        "bold": true,
        "italic": false,
        "underline": false,
        "uppercase": false,
        "linespace": 0,
        "letterspace": 0,
        "font": {
          "name": "Arial",
          "content": "arial.woff"
        },
        "fill": {
          "type": "color",
          "value": "#000000"
        }
      }
    },
    {
      "name": "УТРИМУЙТЕ ТИСК..",
      "type": "text",
      "rect": {
        "x": 1863,
        "y": 1711,
        "w": 842,
        "h": 83,
        "r": 0
      },
      "opacity": 1,
      "locked": false,
      "visible": true,
      "link": "",
      "content": "УТРИМУЙТЕ ТИСК",
      "format": {
        "size": 60,
        "align": "center",
        "bold": true,
        "italic": false,
        "underline": false,
        "uppercase": false,
        "linespace": 0,
        "letterspace": 0,
        "font": {
          "name": "Arial",
          "content": "arial.woff"
        },
        "fill": {
          "type": "color",
          "value": "#000000"
        }
      }
    },
    {
      "name": "УТРИМУЙТЕ ТИСК..",
      "type": "text",
      "rect": {
        "x": 3428,
        "y": 1720,
        "w": 842,
        "h": 83,
        "r": 0
      },
      "opacity": 1,
      "locked": false,
      "visible": true,
      "link": "",
      "content": "УТРИМУЙТЕ ТИСК",
      "format": {
        "size": 60,
        "align": "center",
        "bold": true,
        "italic": false,
        "underline": false,
        "uppercase": false,
        "linespace": 0,
        "letterspace": 0,
        "font": {
          "name": "Arial",
          "content": "arial.woff"
        },
        "fill": {
          "type": "color",
          "value": "#000000"
        }
      }
    },
    {
      "name": "УТРИМУЙТЕ ТИСК..",
      "type": "text",
      "rect": {
        "x": 3361,
        "y": 3207,
        "w": 842,
        "h": 83,
        "r": 0
      },
      "opacity": 1,
      "locked": false,
      "visible": true,
      "link": "",
      "content": "УТРИМУЙТЕ ТИСК",
      "format": {
        "size": 60,
        "align": "center",
        "bold": true,
        "italic": false,
        "underline": false,
        "uppercase": false,
        "linespace": 0,
        "letterspace": 0,
        "font": {
          "name": "Arial",
          "content": "arial.woff"
        },
        "fill": {
          "type": "color",
          "value": "#000000"
        }
      }
    },
    {
      "name": "УТРИМУЙТЕ ТИСК..",
      "type": "text",
      "rect": {
        "x": 1880,
        "y": 5684,
        "w": 842,
        "h": 83,
        "r": 0
      },
      "opacity": 1,
      "locked": false,
      "visible": true,
      "link": "",
      "content": "УТРИМУЙТЕ ТИСК",
      "format": {
        "size": 60,
        "align": "center",
        "bold": true,
        "italic": false,
        "underline": false,
        "uppercase": false,
        "linespace": 0,
        "letterspace": 0,
        "font": {
          "name": "Arial",
          "content": "arial.woff"
        },
        "fill": {
          "type": "color",
          "value": "#000000"
        }
      }
    },
    {
      "name": "Elastic Bandage Pressure Bar YouTube QR PNG.png",
      "type": "image",
      "rect": {
        "x": 2886,
        "y": 100,
        "w": 574,
        "h": 574,
        "r": 0
      },
      "opacity": 1,
      "locked": false,
      "visible": true,
      "link": "",
      "content": "a450a89a4fa0.png"
    },
    {
      "name": "LAST UPDATED",
      "type": "text",
      "rect": {
        "x": 292,
        "y": 6440,
        "w": 3200,
        "h": 92,
        "r": 0
      },
      "opacity": 1,
      "locked": true,
      "visible": true,
      "link": "",
      "content": "https://github.com/farrellgraymond/TCCC-Pixlr                     LAST UPDATED: 2023-11-05T14:36:33Z",
      "format": {
        "size": 64,
        "align": "left",
        "bold": true,
        "italic": false,
        "underline": false,
        "uppercase": false,
        "linespace": 0,
        "letterspace": 0,
        "font": {
          "name": "Arial",
          "content": "arial.woff"
        },
        "fill": {
          "type": "color",
          "value": "#000000"
        }
      }
    }
  ]
}
