{
  "id": "7808fc9a-79d7-4045-b411-2ac1a8bd5e1c",
  "name": "31 Pt1 Tourniquet Conversion PNG",
  "type": "document",
  "unit": "pixel",
  "width": 5100,
  "height": 6600,
  "stack": [
    {
      "name": "Background",
      "type": "image",
      "rect": {
        "x": 0,
        "y": 0,
        "w": 5100,
        "h": 6600,
        "r": 0
      },
      "opacity": 1,
      "locked": true,
      "visible": true,
      "link": "",
      "content": "538abe424e4e.png"
    },
    {
      "name": "Shape 48",
      "type": "shape",
      "rect": {
        "x": 312,
        "y": 3884,
        "w": 158,
        "h": 119,
        "r": 0
      },
      "opacity": 1,
      "locked": false,
      "visible": true,
      "link": "",
      "format": {
        "variant": "rectangle",
        "fill": {
          "type": "color",
          "value": "#423e3b"
        }
      }
    },
    {
      "name": "Shape 45",
      "type": "shape",
      "rect": {
        "x": 3385,
        "y": 2404,
        "w": 159,
        "h": 127,
        "r": 0
      },
      "opacity": 1,
      "locked": false,
      "visible": true,
      "link": "",
      "format": {
        "variant": "rectangle",
        "radii": 20,
        "fill": {
          "type": "color",
          "value": "#423e3b"
        }
      }
    },
    {
      "name": "03.1..",
      "type": "text",
      "rect": {
        "x": 3332,
        "y": 2420,
        "w": 278,
        "h": 106,
        "r": 0
      },
      "opacity": 1,
      "locked": false,
      "visible": true,
      "link": "",
      "content": "03.1",
      "format": {
        "size": 80,
        "align": "center",
        "bold": true,
        "italic": false,
        "underline": false,
        "uppercase": false,
        "linespace": 0,
        "letterspace": 0,
        "font": {
          "name": "Arial",
          "content": "arial.woff"
        },
        "fill": {
          "type": "color",
          "value": "#ffffff"
        }
      }
    },
    {
      "name": "03.2..",
      "type": "text",
      "rect": {
        "x": 251,
        "y": 3898,
        "w": 278,
        "h": 106,
        "r": 0
      },
      "opacity": 1,
      "locked": false,
      "visible": true,
      "link": "",
      "content": "03.2",
      "format": {
        "size": 80,
        "align": "center",
        "bold": true,
        "italic": false,
        "underline": false,
        "uppercase": false,
        "linespace": 0,
        "letterspace": 0,
        "font": {
          "name": "Arial",
          "content": "arial.woff"
        },
        "fill": {
          "type": "color",
          "value": "#ffffff"
        }
      }
    },
    {
      "name": "Продовження на наступній ..",
      "type": "text",
      "rect": {
        "x": 3445,
        "y": 6247,
        "w": 1420,
        "h": 105,
        "r": 0
      },
      "opacity": 1,
      "locked": false,
      "visible": true,
      "link": "",
      "content": "Продовження на наступній сторінці…",
      "format": {
        "size": 76,
        "align": "left",
        "bold": true,
        "italic": false,
        "underline": false,
        "uppercase": false,
        "linespace": 0,
        "letterspace": 0,
        "font": {
          "name": "Arial",
          "content": "arial.woff"
        },
        "fill": {
          "type": "color",
          "value": "#000000"
        }
      }
    },
    {
      "name": "Помістіть подушечку компр..",
      "type": "text",
      "rect": {
        "x": 3558,
        "y": 5460,
        "w": 1325,
        "h": 401,
        "r": 0
      },
      "opacity": 1,
      "locked": false,
      "visible": true,
      "link": "",
      "content": "Помістіть подушечку компресійного бандажа безпосередньо на рану або на попередньо накладену гемостатичну пов’язку, продовжуючи здійснювати прямий тиск на рану.",
      "format": {
        "size": 76,
        "align": "left",
        "bold": true,
        "italic": false,
        "underline": false,
        "uppercase": false,
        "linespace": -0.22,
        "letterspace": 0,
        "font": {
          "name": "Arial",
          "content": "arial.woff"
        },
        "fill": {
          "type": "color",
          "value": "#000000"
        }
      }
    },
    {
      "name": "Вийміть компресійний банд..",
      "type": "text",
      "rect": {
        "x": 2036,
        "y": 5460,
        "w": 1160,
        "h": 179,
        "r": 0
      },
      "opacity": 1,
      "locked": false,
      "visible": true,
      "link": "",
      "content": "Вийміть компресійний бандаж з упаковки.",
      "format": {
        "size": 76,
        "align": "left",
        "bold": true,
        "italic": false,
        "underline": false,
        "uppercase": false,
        "linespace": -0.22,
        "letterspace": 0,
        "font": {
          "name": "Arial",
          "content": "arial.woff"
        },
        "fill": {
          "type": "color",
          "value": "#000000"
        }
      }
    },
    {
      "name": "Після тампонування рани п..",
      "type": "text",
      "rect": {
        "x": 484,
        "y": 5460,
        "w": 1252,
        "h": 327,
        "r": 0
      },
      "opacity": 1,
      "locked": false,
      "visible": true,
      "link": "",
      "content": "Після тампонування рани продовжуйте з силою тиснути на рану руками протягом щонайменше 3 хвилин.",
      "format": {
        "size": 76,
        "align": "left",
        "bold": true,
        "italic": false,
        "underline": false,
        "uppercase": false,
        "linespace": -0.22,
        "letterspace": 0,
        "font": {
          "name": "Arial",
          "content": "arial.woff"
        },
        "fill": {
          "type": "color",
          "value": "#000000"
        }
      }
    },
    {
      "name": "ПРИМІТКА ДО КРОКУ 4: Якщ..",
      "type": "text",
      "rect": {
        "x": 1193,
        "y": 4372,
        "w": 2299,
        "h": 188,
        "r": 0
      },
      "opacity": 1,
      "locked": false,
      "visible": true,
      "link": "",
      "content": "ПРИМІТКА ДО КРОКУ 4: Якщо у рані є стороннє тіло, зафіксуйте його бинтом. Не виймайте стороннє тіло з рани.  ",
      "format": {
        "size": 76,
        "align": "left",
        "bold": true,
        "italic": false,
        "underline": false,
        "uppercase": false,
        "linespace": -0.1,
        "letterspace": 0,
        "font": {
          "name": "Arial",
          "content": "arial.woff"
        },
        "fill": {
          "type": "color",
          "value": "#000000"
        }
      }
    },
    {
      "name": "ПРИМІТКА ДО КРОКУ 4:..",
      "type": "text",
      "rect": {
        "x": 1193,
        "y": 4372,
        "w": 2299,
        "h": 105,
        "r": 0
      },
      "opacity": 1,
      "locked": false,
      "visible": true,
      "link": "",
      "content": "ПРИМІТКА ДО КРОКУ 4:",
      "format": {
        "size": 76,
        "align": "left",
        "bold": true,
        "italic": false,
        "underline": false,
        "uppercase": false,
        "linespace": -0.1,
        "letterspace": 0,
        "font": {
          "name": "Arial",
          "content": "arial.woff"
        },
        "fill": {
          "type": "color",
          "value": "#f00505"
        }
      },
      "style": {
        "outline": {
          "size": 0.3,
          "color": "#f00505",
          "punch": false,
          "distance": 0,
          "direction": 305
        }
      }
    },
    {
      "name": "ПРИМІТКА ДО КРОКУ 4: Якщ..",
      "type": "text",
      "rect": {
        "x": 3445,
        "y": 4123,
        "w": 1519,
        "h": 437,
        "r": 0
      },
      "opacity": 1,
      "locked": false,
      "visible": true,
      "link": "",
      "content": "ПРИМІТКА ДО КРОКУ 4: Якщо гемостатична пов’язка або бинт не виступають на 3-5 см над шкірою, накладіть додаткову кровоспинну пов’язку або бинт.",
      "format": {
        "size": 76,
        "align": "left",
        "bold": true,
        "italic": false,
        "underline": false,
        "uppercase": false,
        "linespace": -0.1,
        "letterspace": 0,
        "font": {
          "name": "Arial",
          "content": "arial.woff"
        },
        "fill": {
          "type": "color",
          "value": "#000000"
        }
      }
    },
    {
      "name": "ПРИМІТКА ДО КРОКУ 4:..",
      "type": "text",
      "rect": {
        "x": 3445,
        "y": 4123,
        "w": 1519,
        "h": 105,
        "r": 0
      },
      "opacity": 1,
      "locked": false,
      "visible": true,
      "link": "",
      "content": "ПРИМІТКА ДО КРОКУ 4:",
      "format": {
        "size": 76,
        "align": "left",
        "bold": true,
        "italic": false,
        "underline": false,
        "uppercase": false,
        "linespace": -0.1,
        "letterspace": 0,
        "font": {
          "name": "Arial",
          "content": "arial.woff"
        },
        "fill": {
          "type": "color",
          "value": "#f00505"
        }
      },
      "style": {
        "outline": {
          "size": 0.3,
          "color": "#f00505",
          "punch": false,
          "distance": 0,
          "direction": 305
        }
      }
    },
    {
      "name": "Переконайтеся, що гемоста..",
      "type": "text",
      "rect": {
        "x": 3558,
        "y": 3842,
        "w": 1244,
        "h": 253,
        "r": 0
      },
      "opacity": 1,
      "locked": false,
      "visible": true,
      "link": "",
      "content": "Переконайтеся, що гемостатична пов’язка або бинт виступають на 3-5 см над шкірою.",
      "format": {
        "size": 76,
        "align": "left",
        "bold": true,
        "italic": false,
        "underline": false,
        "uppercase": false,
        "linespace": -0.22,
        "letterspace": 0,
        "font": {
          "name": "Arial",
          "content": "arial.woff"
        },
        "fill": {
          "type": "color",
          "value": "#000000"
        }
      }
    },
    {
      "name": "ПРИМІТКА ДО КРОКУ 3: Зап..",
      "type": "text",
      "rect": {
        "x": 500,
        "y": 3852,
        "w": 2668,
        "h": 271,
        "r": 0
      },
      "opacity": 1,
      "locked": false,
      "visible": true,
      "link": "",
      "content": "ПРИМІТКА ДО КРОКУ 3: Заповніть та туго затампонуйте всю порожнину рани, підтримуючи сильний тиск на рану. Може знадобитися більш, ніж одна гемостатична пов’язка або бинт.",
      "format": {
        "size": 76,
        "align": "left",
        "bold": true,
        "italic": false,
        "underline": false,
        "uppercase": false,
        "linespace": -0.1,
        "letterspace": 0,
        "font": {
          "name": "Arial",
          "content": "arial.woff"
        },
        "fill": {
          "type": "color",
          "value": "#000000"
        }
      }
    },
    {
      "name": "ПРИМІТКА ДО КРОКУ 3:..",
      "type": "text",
      "rect": {
        "x": 500,
        "y": 3852,
        "w": 2668,
        "h": 105,
        "r": 0
      },
      "opacity": 1,
      "locked": false,
      "visible": true,
      "link": "",
      "content": "ПРИМІТКА ДО КРОКУ 3:",
      "format": {
        "size": 76,
        "align": "left",
        "bold": true,
        "italic": false,
        "underline": false,
        "uppercase": false,
        "linespace": -0.1,
        "letterspace": 0,
        "font": {
          "name": "Arial",
          "content": "arial.woff"
        },
        "fill": {
          "type": "color",
          "value": "#f00505"
        }
      },
      "style": {
        "outline": {
          "size": 0.3,
          "color": "#f00505",
          "punch": false,
          "distance": 0,
          "direction": 305
        }
      }
    },
    {
      "name": "Щільно затампонуйте рану ..",
      "type": "text",
      "rect": {
        "x": 3568,
        "y": 2362,
        "w": 1180,
        "h": 179,
        "r": 0
      },
      "opacity": 1,
      "locked": false,
      "visible": true,
      "link": "",
      "content": "Щільно затампонуйте рану гемостатичним матеріалом.",
      "format": {
        "size": 76,
        "align": "left",
        "bold": true,
        "italic": false,
        "underline": false,
        "uppercase": false,
        "linespace": -0.22,
        "letterspace": 0,
        "font": {
          "name": "Arial",
          "content": "arial.woff"
        },
        "fill": {
          "type": "color",
          "value": "#000000"
        }
      }
    },
    {
      "name": "ПРИМІТКА: Якщо гемостати..",
      "type": "text",
      "rect": {
        "x": 1840,
        "y": 2664,
        "w": 1552,
        "h": 271,
        "r": 0
      },
      "opacity": 1,
      "locked": false,
      "visible": true,
      "link": "",
      "content": "ПРИМІТКА: Якщо гемостатична пов’язка або бинт недоступні, використовуйте чисту суху тканину.",
      "format": {
        "size": 76,
        "align": "left",
        "bold": true,
        "italic": false,
        "underline": false,
        "uppercase": false,
        "linespace": -0.1,
        "letterspace": 0,
        "font": {
          "name": "Arial",
          "content": "arial.woff"
        },
        "fill": {
          "type": "color",
          "value": "#000000"
        }
      }
    },
    {
      "name": "ПРИМІТКА:..",
      "type": "text",
      "rect": {
        "x": 1840,
        "y": 2664,
        "w": 1552,
        "h": 105,
        "r": 0
      },
      "opacity": 1,
      "locked": false,
      "visible": true,
      "link": "",
      "content": "ПРИМІТКА:",
      "format": {
        "size": 76,
        "align": "left",
        "bold": true,
        "italic": false,
        "underline": false,
        "uppercase": false,
        "linespace": -0.1,
        "letterspace": 0,
        "font": {
          "name": "Arial",
          "content": "arial.woff"
        },
        "fill": {
          "type": "color",
          "value": "#f00505"
        }
      },
      "style": {
        "outline": {
          "size": 0.3,
          "color": "#f00505",
          "punch": false,
          "distance": 0,
          "direction": 305
        }
      }
    },
    {
      "name": "Shape 55 Copy",
      "type": "shape",
      "rect": {
        "x": 3413,
        "y": 1552,
        "w": 841,
        "h": 120,
        "r": 0
      },
      "opacity": 1,
      "locked": false,
      "visible": true,
      "link": "",
      "format": {
        "variant": "rounded",
        "radii": 20,
        "fill": {
          "type": "color",
          "value": "#ffffff"
        }
      },
      "style": {
        "outline": {
          "size": 16,
          "color": "#bd1c1e"
        }
      }
    },
    {
      "name": "Shape 55 Copy",
      "type": "shape",
      "rect": {
        "x": 327,
        "y": 5300,
        "w": 841,
        "h": 120,
        "r": 0
      },
      "opacity": 1,
      "locked": false,
      "visible": true,
      "link": "",
      "format": {
        "variant": "rounded",
        "radii": 20,
        "fill": {
          "type": "color",
          "value": "#ffffff"
        }
      },
      "style": {
        "outline": {
          "size": 16,
          "color": "#bd1c1e"
        }
      }
    },
    {
      "name": "УТРИМУЙТЕ ТИСК..",
      "type": "text",
      "rect": {
        "x": 327,
        "y": 5329,
        "w": 842,
        "h": 83,
        "r": 0
      },
      "opacity": 1,
      "locked": false,
      "visible": true,
      "link": "",
      "content": "УТРИМУЙТЕ ТИСК",
      "format": {
        "size": 60,
        "align": "center",
        "bold": true,
        "italic": false,
        "underline": false,
        "uppercase": false,
        "linespace": 0,
        "letterspace": 0,
        "font": {
          "name": "Arial",
          "content": "arial.woff"
        },
        "fill": {
          "type": "color",
          "value": "#000000"
        }
      }
    },
    {
      "name": "УТРИМУЙТЕ ТИСК..",
      "type": "text",
      "rect": {
        "x": 3413,
        "y": 1580,
        "w": 842,
        "h": 83,
        "r": 0
      },
      "opacity": 1,
      "locked": false,
      "visible": true,
      "link": "",
      "content": "УТРИМУЙТЕ ТИСК",
      "format": {
        "size": 60,
        "align": "center",
        "bold": true,
        "italic": false,
        "underline": false,
        "uppercase": false,
        "linespace": 0,
        "letterspace": 0,
        "font": {
          "name": "Arial",
          "content": "arial.woff"
        },
        "fill": {
          "type": "color",
          "value": "#000000"
        }
      }
    },
    {
      "name": "Вийміть кровоспинний пере..",
      "type": "text",
      "rect": {
        "x": 2016,
        "y": 2362,
        "w": 1244,
        "h": 253,
        "r": 0
      },
      "opacity": 1,
      "locked": false,
      "visible": true,
      "link": "",
      "content": "Вийміть кровоспинний перев’язувальний матеріал або бинт зі стерильної упаковки.",
      "format": {
        "size": 76,
        "align": "left",
        "bold": true,
        "italic": false,
        "underline": false,
        "uppercase": false,
        "linespace": -0.22,
        "letterspace": 0,
        "font": {
          "name": "Arial",
          "content": "arial.woff"
        },
        "fill": {
          "type": "color",
          "value": "#000000"
        }
      }
    },
    {
      "name": "ПРИМІТКА: За потреби зні..",
      "type": "text",
      "rect": {
        "x": 327,
        "y": 2625,
        "w": 1292,
        "h": 188,
        "r": 0
      },
      "opacity": 1,
      "locked": false,
      "visible": true,
      "link": "",
      "content": "ПРИМІТКА: За потреби зніміть одяг та спорядження.",
      "format": {
        "size": 76,
        "align": "left",
        "bold": true,
        "italic": false,
        "underline": false,
        "uppercase": false,
        "linespace": -0.1,
        "letterspace": 0,
        "font": {
          "name": "Arial",
          "content": "arial.woff"
        },
        "fill": {
          "type": "color",
          "value": "#000000"
        }
      }
    },
    {
      "name": "ПРИМІТКА:..",
      "type": "text",
      "rect": {
        "x": 327,
        "y": 2625,
        "w": 1292,
        "h": 105,
        "r": 0
      },
      "opacity": 1,
      "locked": false,
      "visible": true,
      "link": "",
      "content": "ПРИМІТКА:",
      "format": {
        "size": 76,
        "align": "left",
        "bold": true,
        "italic": false,
        "underline": false,
        "uppercase": false,
        "linespace": -0.1,
        "letterspace": 0,
        "font": {
          "name": "Arial",
          "content": "arial.woff"
        },
        "fill": {
          "type": "color",
          "value": "#f00505"
        }
      },
      "style": {
        "outline": {
          "size": 0.3,
          "color": "#f00505",
          "punch": false,
          "distance": 0,
          "direction": 305
        }
      }
    },
    {
      "name": "РОЗКРИЙТЕ місце поранення..",
      "type": "text",
      "rect": {
        "x": 480,
        "y": 2372,
        "w": 1300,
        "h": 253,
        "r": 0
      },
      "opacity": 1,
      "locked": false,
      "visible": true,
      "link": "",
      "content": "РОЗКРИЙТЕ місце поранення, якщо цього не було зроблено раніше.",
      "format": {
        "size": 76,
        "align": "left",
        "bold": true,
        "italic": false,
        "underline": false,
        "uppercase": false,
        "linespace": -0.22,
        "letterspace": 0,
        "font": {
          "name": "Arial",
          "content": "arial.woff"
        },
        "fill": {
          "type": "color",
          "value": "#000000"
        }
      }
    },
    {
      "name": "Подбайте про заходи індив..",
      "type": "text",
      "rect": {
        "x": 588,
        "y": 1167,
        "w": 2316,
        "h": 105,
        "r": 0
      },
      "opacity": 1,
      "locked": false,
      "visible": true,
      "link": "",
      "content": "Подбайте про заходи індивідуального захисту.",
      "format": {
        "size": 76,
        "align": "left",
        "bold": true,
        "italic": false,
        "underline": false,
        "uppercase": false,
        "linespace": -0.22,
        "letterspace": 0,
        "font": {
          "name": "Arial",
          "content": "arial.woff"
        },
        "fill": {
          "type": "color",
          "value": "#000000"
        }
      }
    },
    {
      "name": "ПРИМІТКА: Якщо доступний..",
      "type": "text",
      "rect": {
        "x": 588,
        "y": 1290,
        "w": 2316,
        "h": 188,
        "r": 0
      },
      "opacity": 1,
      "locked": false,
      "visible": true,
      "link": "",
      "content": "ПРИМІТКА: Якщо доступний боєць-рятувальник, скеруйте його вам на допомогу.",
      "format": {
        "size": 76,
        "align": "left",
        "bold": true,
        "italic": false,
        "underline": false,
        "uppercase": false,
        "linespace": -0.1,
        "letterspace": 0,
        "font": {
          "name": "Arial",
          "content": "arial.woff"
        },
        "fill": {
          "type": "color",
          "value": "#000000"
        }
      }
    },
    {
      "name": "ПРИМІТКА:..",
      "type": "text",
      "rect": {
        "x": 588,
        "y": 1290,
        "w": 2316,
        "h": 105,
        "r": 0
      },
      "opacity": 1,
      "locked": false,
      "visible": true,
      "link": "",
      "content": "ПРИМІТКА:",
      "format": {
        "size": 76,
        "align": "left",
        "bold": true,
        "italic": false,
        "underline": false,
        "uppercase": false,
        "linespace": -0.1,
        "letterspace": 0,
        "font": {
          "name": "Arial",
          "content": "arial.woff"
        },
        "fill": {
          "type": "color",
          "value": "#f00505"
        }
      },
      "style": {
        "outline": {
          "size": 0.3,
          "color": "#f00505",
          "punch": false,
          "distance": 0,
          "direction": 305
        }
      }
    },
    {
      "name": "КОНВЕРСІЯ ТУРНІКЕТА..",
      "type": "text",
      "rect": {
        "x": 248,
        "y": 775,
        "w": 4248,
        "h": 273,
        "r": 0
      },
      "opacity": 1,
      "locked": false,
      "visible": true,
      "link": "",
      "content": "КОНВЕРСІЯ ТУРНІКЕТА",
      "format": {
        "size": 200,
        "align": "left",
        "bold": true,
        "italic": false,
        "underline": false,
        "uppercase": false,
        "linespace": 0,
        "letterspace": 0,
        "font": {
          "name": "Arial",
          "content": "arial.woff"
        },
        "fill": {
          "type": "color",
          "value": "#000000"
        }
      }
    },
    {
      "name": "LAST UPDATED",
      "type": "text",
      "rect": {
        "x": 292,
        "y": 6440,
        "w": 3200,
        "h": 92,
        "r": 0
      },
      "opacity": 1,
      "locked": true,
      "visible": true,
      "link": "",
      "content": "https://github.com/farrellgraymond/TCCC-Pixlr                     LAST UPDATED: 2024-05-25T03:52:48Z",
      "format": {
        "size": 64,
        "align": "left",
        "bold": true,
        "italic": false,
        "underline": false,
        "uppercase": false,
        "linespace": 0,
        "letterspace": 0,
        "font": {
          "name": "Arial",
          "content": "arial.woff"
        },
        "fill": {
          "type": "color",
          "value": "#000000"
        }
      }
    }
  ]
}
